git_checkpoint/__init__.py
git_checkpoint/interface.py
git_checkpoint/tracker.py
git_checkpoint-0.1.3.dist-info/LICENSE
git_checkpoint-0.1.3.dist-info/METADATA
git_checkpoint-0.1.3.dist-info/WHEEL
git_checkpoint-0.1.3.dist-info/RECORD
